seya_image_processor/__init__.py
seya_image_processor/image_processor.py
seya_image_processor-0.1.1.dist-info/METADATA
seya_image_processor-0.1.1.dist-info/WHEEL
seya_image_processor-0.1.1.dist-info/top_level.txt
seya_image_processor-0.1.1.dist-info/RECORD
